scikit_dsp_comm-2.1.1.dist-info/licenses/LICENSE.md
sk_dsp_comm/__init__.py
sk_dsp_comm/__version__.py
sk_dsp_comm/ca1thru37.txt
sk_dsp_comm/coeff2header.py
sk_dsp_comm/digitalcom.py
sk_dsp_comm/fec_block.py
sk_dsp_comm/fec_conv.py
sk_dsp_comm/fir_design_helper.py
sk_dsp_comm/iir_design_helper.py
sk_dsp_comm/multirate_helper.py
sk_dsp_comm/sigsys.py
sk_dsp_comm/synchronization.py
scikit_dsp_comm-2.1.1.dist-info/METADATA
scikit_dsp_comm-2.1.1.dist-info/WHEEL
scikit_dsp_comm-2.1.1.dist-info/top_level.txt
scikit_dsp_comm-2.1.1.dist-info/RECORD
