Metadata-Version: 2.4
Name: scikit-dsp-comm
Version: 2.1.1
Summary: DSP and Comm package.
Home-page: https://github.com/mwickert/scikit-dsp-comm
Author: Mark Wickert
Author-email: mwickert@uccs.edu
License: BSD
Requires-Python: >=3.7
License-File: LICENSE.md
Requires-Dist: numpy>=1.20.0
Requires-Dist: matplotlib>=3.0.0
Requires-Dist: scipy>=1.1.0
Provides-Extra: helpers
Requires-Dist: colorama; extra == "helpers"
Requires-Dist: pyaudio; extra == "helpers"
Requires-Dist: ipywidgets; extra == "helpers"
Dynamic: author
Dynamic: author-email
Dynamic: description
Dynamic: description-content-type
Dynamic: home-page
Dynamic: license
Dynamic: license-file
Dynamic: provides-extra
Dynamic: requires-dist
Dynamic: requires-python
Dynamic: summary
